README.rst
setup.py
django_mysql_pool.egg-info/PKG-INFO
django_mysql_pool.egg-info/SOURCES.txt
django_mysql_pool.egg-info/dependency_links.txt
django_mysql_pool.egg-info/top_level.txt
mysql_pool/__init__.py
mysql_pool/base.py
mysql_pool/tests.py