Metadata-Version: 1.0
Name: django-mysql-pool
Version: 0.2
Summary: Django application.
Home-page: https://github.com/andymckay/django-mysql-pool
Author: Andy McKay
Author-email: andym@mozilla.com
License: BSD
Platform: UNKNOWN
